ffclienttest/Birds.py
ffclienttest/Mammals.py
ffclienttest/__init__.py
ffclienttest/ffclienttest.py
ffclienttest-0.6.1.dist-info/LICENSE
ffclienttest-0.6.1.dist-info/METADATA
ffclienttest-0.6.1.dist-info/WHEEL
ffclienttest-0.6.1.dist-info/top_level.txt
ffclienttest-0.6.1.dist-info/RECORD
