Metadata-Version: 2.1
Name: ffclienttest
Version: 0.6.1
Summary: devlopment of python featureflag client
Home-page: https://github.com/tmaslen/featureflagclient-python
Author: Charlie Hodgkinson
Author-email: charlotte.hodgkinson4@gmail.com
License: UNKNOWN
Platform: UNKNOWN
Classifier: Programming Language :: Python :: 3
Classifier: License :: OSI Approved :: Apache Software License
Classifier: Operating System :: OS Independent
Requires-Python: >=3.6
